odoo8_addon_website_menu_by_user_status-8.0.1.1.0.99.dev12-py3.8-nspkg.pth
odoo_addons/website_menu_by_user_status/README.rst
odoo_addons/website_menu_by_user_status/__init__.py
odoo_addons/website_menu_by_user_status/__openerp__.py
odoo_addons/website_menu_by_user_status/i18n/de.po
odoo_addons/website_menu_by_user_status/i18n/el_GR.po
odoo_addons/website_menu_by_user_status/i18n/es.po
odoo_addons/website_menu_by_user_status/i18n/fr.po
odoo_addons/website_menu_by_user_status/i18n/it.po
odoo_addons/website_menu_by_user_status/i18n/pt_BR.po
odoo_addons/website_menu_by_user_status/i18n/ru.po
odoo_addons/website_menu_by_user_status/i18n/sl.po
odoo_addons/website_menu_by_user_status/i18n/website_menu_by_user_status.pot
odoo_addons/website_menu_by_user_status/models/__init__.py
odoo_addons/website_menu_by_user_status/models/website_menu.py
odoo_addons/website_menu_by_user_status/static/description/icon.png
odoo_addons/website_menu_by_user_status/views/website_templates.xml
odoo_addons/website_menu_by_user_status/views/website_views.xml
odoo8_addon_website_menu_by_user_status-8.0.1.1.0.99.dev12.dist-info/METADATA
odoo8_addon_website_menu_by_user_status-8.0.1.1.0.99.dev12.dist-info/WHEEL
odoo8_addon_website_menu_by_user_status-8.0.1.1.0.99.dev12.dist-info/namespace_packages.txt
odoo8_addon_website_menu_by_user_status-8.0.1.1.0.99.dev12.dist-info/top_level.txt
odoo8_addon_website_menu_by_user_status-8.0.1.1.0.99.dev12.dist-info/RECORD
